aliasmate/__init__.py
aliasmate/__main__.py
aliasmate-0.1.5.dist-info/LICENSE
aliasmate-0.1.5.dist-info/METADATA
aliasmate-0.1.5.dist-info/WHEEL
aliasmate-0.1.5.dist-info/entry_points.txt
aliasmate-0.1.5.dist-info/top_level.txt
aliasmate-0.1.5.dist-info/RECORD
