Metadata-Version: 2.1
Name: aliasmate
Version: 0.1.5
Summary: A command-line alias substitution tool
Home-page: https://github.com/maslovw/aliasmate
Author: Slava Maslov
Author-email: maslovw@gmail.com
Classifier: Programming Language :: Python :: 3
Classifier: License :: OSI Approved :: MIT License
Classifier: Operating System :: OS Independent
Requires-Python: >=3.6
License-File: LICENSE
Requires-Dist: PyYAML
